threddsclient/__init__.py
threddsclient/catalog.py
threddsclient/client.py
threddsclient/nodes.py
threddsclient/utils.py
threddsclient-0.4.7.dist-info/licenses/AUTHORS.rst
threddsclient-0.4.7.dist-info/licenses/LICENCE.txt
threddsclient-0.4.7.dist-info/METADATA
threddsclient-0.4.7.dist-info/WHEEL
threddsclient-0.4.7.dist-info/top_level.txt
threddsclient-0.4.7.dist-info/RECORD
