Metadata-Version: 2.4
Name: threddsclient
Version: 0.4.7
Summary: Thredds catalog client
Home-page: https://github.com/bird-house/threddsclient
Download-URL: https://github.com/bird-house/threddsclient
Author: Birdhouse
License: Apache 2.0
Classifier: Development Status :: 3 - Alpha
Classifier: Intended Audience :: Science/Research
Classifier: Operating System :: MacOS :: MacOS X
Classifier: Operating System :: Microsoft :: Windows
Classifier: Operating System :: POSIX
Classifier: Operating System :: OS Independent
Classifier: Programming Language :: Python
Classifier: Programming Language :: Python :: 3
Classifier: Programming Language :: Python :: 3.8
Classifier: Programming Language :: Python :: 3.9
Classifier: Programming Language :: Python :: 3.10
Classifier: Programming Language :: Python :: 3.11
Classifier: Programming Language :: Python :: 3.12
Classifier: Programming Language :: Python :: 3.13
Classifier: Programming Language :: Python :: 3.14
Classifier: Programming Language :: Python :: 3 :: Only
Classifier: Topic :: Scientific/Engineering :: Atmospheric Science
Requires-Python: >=3.8,<4
License-File: LICENCE.txt
License-File: AUTHORS.rst
Requires-Dist: requests
Requires-Dist: beautifulsoup4
Requires-Dist: lxml
Dynamic: author
Dynamic: classifier
Dynamic: description
Dynamic: download-url
Dynamic: home-page
Dynamic: license
Dynamic: license-file
Dynamic: requires-dist
Dynamic: requires-python
Dynamic: summary
